README
setup.py
abus/__init__.py
abus/backup.py
abus/backup_tools.py
abus/config.py
abus/crypto.py
abus/database.py
abus/database_backup_restore.py
abus/database_purge.py
abus/database_rebuild.py
abus/main.py
abus/purge.py
abus/rebuild.py
abus/restore.py
abus/schema.sql
abus/synchronisation.py
abus/test_backups.py
abus/test_config.py
abus/test_crypto.py
abus/test_purge.py
abus/test_rebuild.py
abus/test_restore.py
abus/test_upgrades.py
abus/testbase.py
abus/upgrade-1.sql
abus/upgrade-2.sql
abus/upgrade-3.sql
abus.egg-info/PKG-INFO
abus.egg-info/SOURCES.txt
abus.egg-info/dependency_links.txt
abus.egg-info/entry_points.txt
abus.egg-info/not-zip-safe
abus.egg-info/requires.txt
abus.egg-info/top_level.txt
abus/cornelib/__init__.py
abus/cornelib/_tests.py
abus/cornelib/misc.py
abus/cornelib/schapp.py
abus/cornelib/__init__.py
abus/cornelib/_tests.py
abus/cornelib/misc.py
abus/cornelib/schapp.py