Metadata-Version: 1.1
Name: abus
Version: 10
Summary: Abingdon Backup Script
Home-page: https://pypi.python.org/pypi/abus
Author: Cornelius Grotjahn
Author-email: s1@tempaddr.uk
License: MIT
Platform: UNKNOWN
Classifier: Programming Language :: Python :: 3.6
Classifier: Programming Language :: Python :: 3 :: Only
Classifier: Development Status :: 5 - Production/Stable
Classifier: License :: OSI Approved :: MIT License
Classifier: Topic :: System :: Archiving :: Backup
